sdn_test_simple_car_repository/__init__.py
sdn_test_simple_car_repository/in_memory_simple_car_repository.py
sdn_test_simple_car_repository-1.0.0.dist-info/licenses/LICENSE
sdn_test_simple_car_repository-1.0.0.dist-info/METADATA
sdn_test_simple_car_repository-1.0.0.dist-info/WHEEL
sdn_test_simple_car_repository-1.0.0.dist-info/top_level.txt
sdn_test_simple_car_repository-1.0.0.dist-info/RECORD
